{
	"id": "35a63fb1-386e-4608-9133-19f7c883c015",
	"name": "SailPointInterface",
	"values": [
		{
			"key": "URL",
			"value": "https://lp1-ap-51664839:8443/appscan/api",
			"enabled": true
		},
		{
			"key": "AuthorizationToken",
			"value": "",
			"enabled": true
		},
		{
			"key": "accountid",
			"value": "",
			"enabled": true
		},
		{
			"key": "entitlementid",
			"value": "",
			"enabled": true
		}
	],
	"_postman_variable_scope": "environment",
	"_postman_exported_at": "2022-02-02T17:13:39.452Z",
	"_postman_exported_using": "Postman/9.11.0"
}